hello_world_henrique/__init__.py
hello_world_henrique/tools/__init__.py
hello_world_henrique/tools/hello_world_tool_henrique.py
hello_world_henrique/tools/utils.py
hello_world_henrique/yamls/hello_world_tool_henrique.yaml
tests/__init__.py
tests/test_hello_world_tool_henrique.py
hello_world_henrique-0.0.1.dist-info/METADATA
hello_world_henrique-0.0.1.dist-info/WHEEL
hello_world_henrique-0.0.1.dist-info/entry_points.txt
hello_world_henrique-0.0.1.dist-info/top_level.txt
hello_world_henrique-0.0.1.dist-info/RECORD
